pipefolio/__init__.py
pipefolio/data.py
pipefolio/enums.py
pipefolio/mixins.py
pipefolio/adaptor/__init__.py
pipefolio/adaptor/weight_arr.py
pipefolio/adaptor/weight_map.py
pipefolio/optimizer/__init__.py
pipefolio/optimizer/equal.py
pipefolio/optimizer/inverse_vlty.py
pipefolio/optimizer/max_ratio.py
pipefolio/optimizer/max_ret.py
pipefolio/optimizer/mean_risk.py
pipefolio/optimizer/min_risk.py
pipefolio/optimizer/risk_averse.py
pipefolio/selector/__init__.py
pipefolio/selector/ann_vlty.py
pipefolio/selector/avg_trade_value.py
pipefolio/selector/tot_ret.py
pipefolio/transformer/__init__.py
pipefolio/transformer/price_to_return.py
pipefolio-0.0.1.dist-info/LICENSE
pipefolio-0.0.1.dist-info/METADATA
pipefolio-0.0.1.dist-info/WHEEL
pipefolio-0.0.1.dist-info/top_level.txt
pipefolio-0.0.1.dist-info/RECORD
