Metadata-Version: 2.2
Name: pipefolio
Version: 0.0.1
Summary: A Pipeline-Oriented Portfolio Optimization Framework
Author: Kachain Fuangsung
Author-email: kachain.f@outlook.com
License: MIT License
Project-URL: Homepage, https://github.com/kfuangsung/pipefolio
Project-URL: Documentation, https://kfuangsung.github.io/pipefolio
Project-URL: Repository, https://github.com/kfuangsung/pipefolio.git
Project-URL: Issues, https://github.com/kfuangsung/pipefolio/issues
Project-URL: Changelog, https://github.com/kfuangsung/pipefolio/blob/main/CHANGELOG.md
Classifier: Programming Language :: Python :: 3
Requires-Python: >=3.12
License-File: LICENSE
Requires-Dist: scikit-learn<2,>1
Requires-Dist: skfolio<1
Requires-Dist: pydantic<3,>=2
Requires-Dist: Deprecated<2,>=1.2
Requires-Dist: empyrical-reloaded>=0.5
